envappconfig/__init__.py
envappconfig/envappconfig.py
envappconfig/exceptions.py
envappconfig-2024.339.1353.dist-info/LICENSE
envappconfig-2024.339.1353.dist-info/METADATA
envappconfig-2024.339.1353.dist-info/WHEEL
envappconfig-2024.339.1353.dist-info/RECORD
