Metadata-Version: 2.1
Name: envappconfig
Version: 2024.339.1353
Summary: Simple app configuration via environment variables, in the spirit of argparse.
Home-page: https://github.com/spectriclabs/envappconfig
License: Apache-2.0
Author: Spectric Labs
Author-email: foss@spectric.com
Requires-Python: >=3.6,<4.0
Classifier: License :: OSI Approved :: Apache Software License
Classifier: Programming Language :: Python :: 3
Classifier: Programming Language :: Python :: 3.6
Classifier: Programming Language :: Python :: 3.7
Classifier: Programming Language :: Python :: 3.8
Classifier: Programming Language :: Python :: 3.9
Classifier: Programming Language :: Python :: 3.10
Classifier: Programming Language :: Python :: 3.11
Classifier: Programming Language :: Python :: 3.12
Classifier: Programming Language :: Python :: 3.13
